{
	"categories" : [
		{"name": "Statement"},
		{"name": "Expression"},
		{"name": "Function"}
	],
	"constructions" : [
		{"name": "Assign", "text": "<var> = <expr>", "category": "Statement", "tclass" : "StatementBlock" },
		{"name": "Condition", "text": "if <cond> : <scope>", "category": "Statement", "tclass" : "ConditionBlock"  },
		{"name": "Loop", "text": "for <cond> : <scope>", "category": "Statement" , "tclass" : "LoopBlock" },
		{"name": "Value", "text": "<val>", "category": "Expression" , "tclass" : "ValueBlock" },
		{"name": "Variable", "text": "<var>", "category": "Expression", "tclass" : "VariableBlock"  },
		{"name": "GlobalVariable", "text": "<glob_var>", "category": "Expression", "tclass" : "GlobalVariableBlock"  },
		{"name": "BinOp", "text": "<expr> <oper> <expr>", "category": "Expression", "tclass" : "BinaryOperatorBlock"  },
		{"name": "Braces", "text": "(<expr>)", "category": "Expression" , "tclass" : "BracesBlock" },
		{"name": "Function", "text": "<func_name> (<expr>, ...)", "category": "Function" , "tclass" : "FunctionBlock" }
	]
}